jsa_utils/__init__.py
jsa_utils/assets.py
jsa_utils/settings.py
jsa_utils-0.0.1.5.dist-info/LICENSE
jsa_utils-0.0.1.5.dist-info/METADATA
jsa_utils-0.0.1.5.dist-info/WHEEL
jsa_utils-0.0.1.5.dist-info/top_level.txt
jsa_utils-0.0.1.5.dist-info/RECORD
